LICENSE
README.md
setup.cfg
setup.py
omniply/__init__.py
omniply.egg-info/PKG-INFO
omniply.egg-info/SOURCES.txt
omniply.egg-info/dependency_links.txt
omniply.egg-info/requires.txt
omniply.egg-info/top_level.txt
omniply/_future/__init__.py
omniply/_future/common.py
omniply/_future/specification.py
omniply/_future/wrappers.py
omniply/apps/__init__.py
omniply/apps/gaps.py
omniply/apps/guides.py
omniply/apps/simple.py
omniply/apps/staging.py
omniply/apps/templating.py
omniply/apps/unit_test.py
omniply/apps/decisions/__init__.py
omniply/apps/decisions/abstract.py
omniply/apps/decisions/chains.py
omniply/apps/decisions/decisions.py
omniply/apps/decisions/errors.py
omniply/apps/decisions/imports.py
omniply/apps/decisions/op.py
omniply/apps/decisions/unit_test.py
omniply/apps/training/__init__.py
omniply/apps/training/abstract.py
omniply/apps/training/guru.py
omniply/apps/training/imports.py
omniply/apps/training/innovators.py
omniply/apps/training/moguls.py
omniply/core/__init__.py
omniply/core/abstract.py
omniply/core/errors.py
omniply/core/gadgets.py
omniply/core/gaggles.py
omniply/core/games.py
omniply/core/gates.py
omniply/core/genetics.py
omniply/core/gizmos.py
omniply/core/op.py
omniply/core/tools.py
omniply/core/unit_test.py
omniply/spaces/__init__.py
omniply/spaces/imports.py