Metadata-Version: 2.1
Name: omniply
Version: 0.3.5
Summary: "Omni-ply Versatile Data Management for Rapid AI Prototyping and Research"
Author: Felix Leeb
License: MIT
Classifier: Programming Language :: Python :: 3.10
License-File: LICENSE
Provides-Extra: test
Requires-Dist: pytest; extra == "test"
